rastervision/core/__init__.py
rastervision/core/box.py
rastervision/core/cli.py
rastervision/core/data_sample.py
rastervision/core/predictor.py
rastervision/core/py.typed
rastervision/core/raster_stats.py
rastervision/core/analyzer/__init__.py
rastervision/core/analyzer/analyzer.py
rastervision/core/analyzer/analyzer_config.py
rastervision/core/analyzer/stats_analyzer.py
rastervision/core/analyzer/stats_analyzer_config.py
rastervision/core/backend/__init__.py
rastervision/core/backend/backend.py
rastervision/core/backend/backend_config.py
rastervision/core/data/__init__.py
rastervision/core/data/class_config.py
rastervision/core/data/dataset_config.py
rastervision/core/data/scene.py
rastervision/core/data/scene_config.py
rastervision/core/data/crs_transformer/__init__.py
rastervision/core/data/crs_transformer/crs_transformer.py
rastervision/core/data/crs_transformer/identity_crs_transformer.py
rastervision/core/data/crs_transformer/rasterio_crs_transformer.py
rastervision/core/data/label/__init__.py
rastervision/core/data/label/chip_classification_labels.py
rastervision/core/data/label/labels.py
rastervision/core/data/label/object_detection_labels.py
rastervision/core/data/label/semantic_segmentation_labels.py
rastervision/core/data/label/utils.py
rastervision/core/data/label/tfod_utils/__init__.py
rastervision/core/data/label/tfod_utils/np_box_list.py
rastervision/core/data/label/tfod_utils/np_box_list_ops.py
rastervision/core/data/label/tfod_utils/np_box_ops.py
rastervision/core/data/label_source/__init__.py
rastervision/core/data/label_source/chip_classification_label_source.py
rastervision/core/data/label_source/chip_classification_label_source_config.py
rastervision/core/data/label_source/label_source.py
rastervision/core/data/label_source/label_source_config.py
rastervision/core/data/label_source/object_detection_label_source.py
rastervision/core/data/label_source/object_detection_label_source_config.py
rastervision_core-0.31.1.dist-info/METADATA
rastervision_core-0.31.1.dist-info/WHEEL
rastervision_core-0.31.1.dist-info/top_level.txt
rastervision_core-0.31.1.dist-info/RECORD
