Metadata-Version: 2.1
Name: rastervision_core
Version: 0.31.1
Summary: A rastervision plugin that adds geospatial machine learning pipelines
Home-page: https://github.com/azavea/raster-vision
Author: Azavea
Author-email: info@azavea.com
License: Apache License 2.0
Keywords: raster deep-learning ml computer-vision earth-observation geospatial geospatial-processing
Classifier: Intended Audience :: Developers
Classifier: License :: OSI Approved :: Apache Software License
Classifier: Programming Language :: Python
Classifier: Programming Language :: Python :: 3
Requires-Dist: rastervision-pipeline
Requires-Dist: shapely
Requires-Dist: geopandas
Requires-Dist: numpy
Requires-Dist: pillow
Requires-Dist: pyproj
Requires-Dist: rasterio
Requires-Dist: pystac
Requires-Dist: scikit-learn
Requires-Dist: scipy
Requires-Dist: opencv-python-headless
Requires-Dist: tqdm
Requires-Dist: xarray
Requires-Dist: scikit-image
Requires-Dist: boto3
Requires-Dist: stackstac
Requires-Dist: humanize
Requires-Dist: triangle
